flat_api/__init__.py
flat_api/api_client.py
flat_api/api_response.py
flat_api/configuration.py
flat_api/exceptions.py
flat_api/py.typed
flat_api/rest.py
flat_api/api/__init__.py
flat_api/api/account_api.py
flat_api/api/class_api.py
flat_api/api/collection_api.py
flat_api/api/edu_resources_api.py
flat_api/api/group_api.py
flat_api/api/organization_api.py
flat_api/api/score_api.py
flat_api/api/task_api.py
flat_api/api/user_api.py
flat_api/models/__init__.py
flat_api/models/api_access_token.py
flat_api/models/app_scopes.py
flat_api/models/assignment.py
flat_api/models/assignment_copy.py
flat_api/models/assignment_copy_response.py
flat_api/models/assignment_copy_response_capabilities.py
flat_api/models/assignment_copy_response_capabilities_can_publish_in_class_error.py
flat_api/models/assignment_submission.py
flat_api/models/assignment_submission_comment.py
flat_api/models/assignment_submission_comment_creation.py
flat_api/models/assignment_submission_comments.py
flat_api/models/assignment_submission_history.py
flat_api/models/assignment_submission_history_attachment.py
flat_api/models/assignment_submission_history_state.py
flat_api/models/assignment_submission_lti.py
flat_api/models/assignment_submission_playback_inner.py
flat_api/models/assignment_submission_state.py
flat_api/models/assignment_submission_update.py
flat_api/models/assignment_type.py
flat_api/models/assignment_update.py
flat_api/models/class_assignment.py
flat_api/models/class_assignment_canvas.py
flat_api/models/class_assignment_lti.py
flat_api/models/class_assignment_mfc.py
flat_api/models/class_assignment_update.py
flat_api/models/class_assignment_update_google_classroom.py
flat_api/models/class_assignment_update_microsoft_graph.py
flat_api/models/class_attachment_creation.py
flat_api/models/class_creation.py
flat_api/models/class_details.py
flat_api/models/class_details_canvas.py
flat_api/models/class_details_clever.py
flat_api/models/class_details_google_classroom.py
flat_api-1.1.3.dist-info/LICENSE
flat_api-1.1.3.dist-info/METADATA
flat_api-1.1.3.dist-info/WHEEL
flat_api-1.1.3.dist-info/top_level.txt
flat_api-1.1.3.dist-info/RECORD
